djangorestframework_constant_field-0.9.1.dist-info/DESCRIPTION.rst
djangorestframework_constant_field-0.9.1.dist-info/METADATA
djangorestframework_constant_field-0.9.1.dist-info/RECORD
djangorestframework_constant_field-0.9.1.dist-info/WHEEL
djangorestframework_constant_field-0.9.1.dist-info/metadata.json
djangorestframework_constant_field-0.9.1.dist-info/top_level.txt
rest_framework_constant/__init__.py
rest_framework_constant/fields.py
tests/__init__.py
tests/test_serializer.py
