Metadata-Version: 2.0
Name: djangorestframework-constant-field
Version: 0.9.1
Summary: A simple Constant Field definition for Django REST Framework
Home-page: https://github.com/mypebble/djangorestframework-constant-field.git
Author: Scott Walton
Author-email: scott.walton@mypebble.co.uk
License: Public Domain
Platform: UNKNOWN
Classifier: Development Status :: 5 - Production/Stable
Classifier: Programming Language :: Python
Classifier: Programming Language :: Python :: 2.7
Classifier: Programming Language :: Python :: 3
Classifier: Framework :: Django
Classifier: Framework :: Django :: 1.9
Classifier: Framework :: Django :: 1.10
Classifier: Framework :: Django :: 1.11
Requires-Dist: django
Requires-Dist: djangorestframework
